[
    {
        "id": 1,
        "name": "フレンドポイント召喚",
        "imageId": 70263,
        "priority": 1,
        "warId": -1,
        "gachaSlot": 1000010,
        "type": 3,
        "shopId1": 1,
        "shopId2": 0,
        "rarityId": 14,
        "baseId": 30016,
        "adjustId": 0,
        "pickupId": 0,
        "ticketItemId": 0,
        "gachaGroupId": 0,
        "drawNum1": 1,
        "drawNum2": 0,
        "extraGroupId1": 0,
        "extraGroupId2": 0,
        "extraAddCount1": 0,
        "extraAddCount2": 0,
        "freeDrawFlag": 1,
        "maxDrawNum": 0,
        "beforeGachaId": 0,
        "beforeDrawNum": 0,
        "openedAt": 1435676400,
        "closedAt": 1911653999,
        "condQuestId": 1000002,
        "condQuestPhase": 1,
        "detailUrl": "",
        "bannerQuestId": 1000002,
        "bannerQuestPhase": 1,
        "flag": 0,
        "gachaListGroupId": 1,
        "featurePickupRarityGroupId": 10001
    },
    {
        "id": 101,
        "name": "チュートリアル召喚",
        "imageId": 103,
        "priority": 11,
        "warId": 100,
        "gachaSlot": 2000010,
        "type": 1,
        "shopId1": 4,
        "shopId2": 5,
        "rarityId": 2,
        "baseId": 1003,
        "adjustId": 0,
        "pickupId": 0,
        "ticketItemId": 4001,
        "gachaGroupId": 0,
        "drawNum1": 1,
        "drawNum2": 11,
        "extraGroupId1": 0,
        "extraGroupId2": 0,
        "extraAddCount1": 1,
        "extraAddCount2": 0,
        "freeDrawFlag": 0,
        "maxDrawNum": 1,
        "beforeGachaId": 0,
        "beforeDrawNum": 0,
        "openedAt": 1435676400,
        "closedAt": 1911653999,
        "condQuestId": 1000002,
        "condQuestPhase": 1,
        "detailUrl": "",
        "bannerQuestId": 1000002,
        "bannerQuestPhase": 1,
        "flag": 0,
        "gachaListGroupId": 0,
        "featurePickupRarityGroupId": 10001
    },
    {
        "id": 501,
        "name": "スタートダッシュ期間限定★5確定召喚",
        "imageId": 500,
        "priority": 5000360,
        "warId": 100,
        "gachaSlot": 5000360,
        "type": 7,
        "shopId1": 9,
        "shopId2": 0,
        "rarityId": 3,
        "baseId": 20201,
        "adjustId": 0,
        "pickupId": 0,
        "ticketItemId": 0,
        "gachaGroupId": 0,
        "drawNum1": 11,
        "drawNum2": 0,
        "extraGroupId1": 0,
        "extraGroupId2": 0,
        "extraAddCount1": 1,
        "extraAddCount2": 0,
        "freeDrawFlag": 0,
        "maxDrawNum": 1,
        "beforeGachaId": 101,
        "beforeDrawNum": 1,
        "openedAt": 1743238800,
        "closedAt": 1911653999,
        "condQuestId": 1000002,
        "condQuestPhase": 1,
        "detailUrl": "/25_vwezy/start_dash_s",
        "bannerQuestId": 1000002,
        "bannerQuestPhase": 1,
        "flag": 16,
        "gachaListGroupId": 1,
        "featurePickupRarityGroupId": 10001
    },
    {
        "id": 21001,
        "name": "ストーリー召喚",
        "imageId": 264,
        "priority": 1001,
        "warId": 100,
        "gachaSlot": 2000010,
        "type": 1,
        "shopId1": 4,
        "shopId2": 5,
        "rarityId": 3,
        "baseId": 10040,
        "adjustId": 0,
        "pickupId": 0,
        "ticketItemId": 4001,
        "gachaGroupId": 0,
        "drawNum1": 1,
        "drawNum2": 11,
        "extraGroupId1": 1,
        "extraGroupId2": 0,
        "extraAddCount1": 1,
        "extraAddCount2": 0,
        "freeDrawFlag": 0,
        "maxDrawNum": 0,
        "beforeGachaId": 101,
        "beforeDrawNum": 1,
        "openedAt": 1443157200,
        "closedAt": 1911653999,
        "condQuestId": 1000002,
        "condQuestPhase": 1,
        "detailUrl": "/story",
        "bannerQuestId": 1000002,
        "bannerQuestPhase": 1,
        "flag": 0,
        "gachaListGroupId": 1,
        "featurePickupRarityGroupId": 10001
    },
    {
        "id": 50027341,
        "name": "「春の新米マスター応援キャンペーン2025！」 \nモルガンピックアップ召喚",
        "imageId": 82895,
        "priority": 3000550,
        "warId": 100,
        "gachaSlot": 3000550,
        "type": 1,
        "shopId1": 4,
        "shopId2": 5,
        "rarityId": 3,
        "baseId": 10040,
        "adjustId": 50014731,
        "pickupId": 50017772,
        "ticketItemId": 4001,
        "gachaGroupId": 0,
        "drawNum1": 1,
        "drawNum2": 11,
        "extraGroupId1": 917,
        "extraGroupId2": 0,
        "extraAddCount1": 1,
        "extraAddCount2": 0,
        "freeDrawFlag": 0,
        "maxDrawNum": 0,
        "beforeGachaId": 101,
        "beforeDrawNum": 1,
        "openedAt": 1743238800,
        "closedAt": 1744430399,
        "condQuestId": 1000002,
        "condQuestPhase": 1,
        "detailUrl": "/25_xzfqx/n_m_s_cp2025",
        "bannerQuestId": 1000002,
        "bannerQuestPhase": 1,
        "flag": 34,
        "gachaListGroupId": 1,
        "featurePickupRarityGroupId": 10002
    },
    {
        "id": 50027351,
        "name": "復刻 ぐだぐだ龍馬危機一髪！ 坂本龍馬(ランサー)ピックアップ召喚",
        "imageId": 82896,
        "priority": 4000190,
        "warId": 100,
        "gachaSlot": 4000190,
        "type": 1,
        "shopId1": 4,
        "shopId2": 5,
        "rarityId": 3,
        "baseId": 10040,
        "adjustId": 50014761,
        "pickupId": 50017802,
        "ticketItemId": 4001,
        "gachaGroupId": 0,
        "drawNum1": 1,
        "drawNum2": 11,
        "extraGroupId1": 920,
        "extraGroupId2": 0,
        "extraAddCount1": 1,
        "extraAddCount2": 0,
        "freeDrawFlag": 0,
        "maxDrawNum": 0,
        "beforeGachaId": 101,
        "beforeDrawNum": 1,
        "openedAt": 1744102800,
        "closedAt": 1745380799,
        "condQuestId": 1000002,
        "condQuestPhase": 1,
        "detailUrl": "/25_rthur/re_kiki_b",
        "bannerQuestId": 1000002,
        "bannerQuestPhase": 1,
        "flag": 34,
        "gachaListGroupId": 1,
        "featurePickupRarityGroupId": 10001
    },
    {
        "id": 50027361,
        "name": "復刻 ぐだぐだ龍馬危機一髪！ 高杉晋作ピックアップ召喚",
        "imageId": 82897,
        "priority": 4000200,
        "warId": 100,
        "gachaSlot": 4000200,
        "type": 1,
        "shopId1": 4,
        "shopId2": 5,
        "rarityId": 3,
        "baseId": 10040,
        "adjustId": 50014771,
        "pickupId": 50017812,
        "ticketItemId": 4001,
        "gachaGroupId": 0,
        "drawNum1": 1,
        "drawNum2": 11,
        "extraGroupId1": 921,
        "extraGroupId2": 0,
        "extraAddCount1": 1,
        "extraAddCount2": 0,
        "freeDrawFlag": 0,
        "maxDrawNum": 0,
        "beforeGachaId": 101,
        "beforeDrawNum": 1,
        "openedAt": 1744362000,
        "closedAt": 1745380799,
        "condQuestId": 1000002,
        "condQuestPhase": 1,
        "detailUrl": "/25_rthur/re_kiki_c",
        "bannerQuestId": 1000002,
        "bannerQuestPhase": 1,
        "flag": 34,
        "gachaListGroupId": 1,
        "featurePickupRarityGroupId": 10001
    },
    {
        "id": 50027371,
        "name": "復刻 ぐだぐだ龍馬危機一髪！ 出雲阿国ピックアップ召喚",
        "imageId": 82898,
        "priority": 4000180,
        "warId": 100,
        "gachaSlot": 4000180,
        "type": 1,
        "shopId1": 4,
        "shopId2": 5,
        "rarityId": 3,
        "baseId": 10040,
        "adjustId": 50014781,
        "pickupId": 50017822,
        "ticketItemId": 4001,
        "gachaGroupId": 0,
        "drawNum1": 1,
        "drawNum2": 11,
        "extraGroupId1": 922,
        "extraGroupId2": 0,
        "extraAddCount1": 1,
        "extraAddCount2": 0,
        "freeDrawFlag": 0,
        "maxDrawNum": 0,
        "beforeGachaId": 101,
        "beforeDrawNum": 1,
        "openedAt": 1743584400,
        "closedAt": 1745380799,
        "condQuestId": 1000002,
        "condQuestPhase": 1,
        "detailUrl": "/25_rthur/re_kiki_a",
        "bannerQuestId": 1000002,
        "bannerQuestPhase": 1,
        "flag": 34,
        "gachaListGroupId": 1,
        "featurePickupRarityGroupId": 10001
    },
    {
        "id": 50027381,
        "name": "3100万DL記念 レディ･アヴァロンピックアップ召喚",
        "imageId": 82899,
        "priority": 7000010,
        "warId": 100,
        "gachaSlot": 7000010,
        "type": 1,
        "shopId1": 4,
        "shopId2": 5,
        "rarityId": 3,
        "baseId": 10040,
        "adjustId": 50014971,
        "pickupId": 50018022,
        "ticketItemId": 4001,
        "gachaGroupId": 0,
        "drawNum1": 1,
        "drawNum2": 11,
        "extraGroupId1": 942,
        "extraGroupId2": 0,
        "extraAddCount1": 1,
        "extraAddCount2": 0,
        "freeDrawFlag": 0,
        "maxDrawNum": 0,
        "beforeGachaId": 101,
        "beforeDrawNum": 1,
        "openedAt": 1744189200,
        "closedAt": 1745380799,
        "condQuestId": 1000002,
        "condQuestPhase": 1,
        "detailUrl": "/25_ojfel/3100man",
        "bannerQuestId": 1000002,
        "bannerQuestPhase": 1,
        "flag": 34,
        "gachaListGroupId": 1,
        "featurePickupRarityGroupId": 10002
    },
    {
        "id": 50027401,
        "name": "「巡霊の祝祭 第11弾」 武田信玄(武田晴信)ピックアップ召喚",
        "imageId": 82901,
        "priority": 3000570,
        "warId": 100,
        "gachaSlot": 3000570,
        "type": 1,
        "shopId1": 4,
        "shopId2": 5,
        "rarityId": 3,
        "baseId": 10040,
        "adjustId": 50014751,
        "pickupId": 50017792,
        "ticketItemId": 4001,
        "gachaGroupId": 0,
        "drawNum1": 1,
        "drawNum2": 11,
        "extraGroupId1": 919,
        "extraGroupId2": 0,
        "extraAddCount1": 1,
        "extraAddCount2": 0,
        "freeDrawFlag": 0,
        "maxDrawNum": 0,
        "beforeGachaId": 101,
        "beforeDrawNum": 1,
        "openedAt": 1743930000,
        "closedAt": 1744516799,
        "condQuestId": 1000002,
        "condQuestPhase": 1,
        "detailUrl": "/25_rropa/feasts_cp11_b",
        "bannerQuestId": 1000002,
        "bannerQuestPhase": 1,
        "flag": 34,
        "gachaListGroupId": 1,
        "featurePickupRarityGroupId": 10001
    },
    {
        "id": 50027491,
        "name": "【週替り】 アビゲイル･ウィリアムズピックアップ召喚",
        "imageId": 82910,
        "priority": 2501280,
        "warId": 100,
        "gachaSlot": 2501280,
        "type": 1,
        "shopId1": 4,
        "shopId2": 5,
        "rarityId": 3,
        "baseId": 10040,
        "adjustId": 50014861,
        "pickupId": 50017912,
        "ticketItemId": 4001,
        "gachaGroupId": 0,
        "drawNum1": 1,
        "drawNum2": 11,
        "extraGroupId1": 931,
        "extraGroupId2": 0,
        "extraAddCount1": 1,
        "extraAddCount2": 0,
        "freeDrawFlag": 0,
        "maxDrawNum": 0,
        "beforeGachaId": 101,
        "beforeDrawNum": 1,
        "openedAt": 1744016400,
        "closedAt": 1744603199,
        "condQuestId": 1000002,
        "condQuestPhase": 1,
        "detailUrl": "/25_fzcix/frnr_pu_a",
        "bannerQuestId": 1000002,
        "bannerQuestPhase": 1,
        "flag": 34,
        "gachaListGroupId": 1,
        "featurePickupRarityGroupId": 10002
    },
    {
        "id": 50027501,
        "name": "【週替り】 葛飾北斎(フォーリナー)ピックアップ召喚",
        "imageId": 82911,
        "priority": 2501270,
        "warId": 100,
        "gachaSlot": 2501270,
        "type": 1,
        "shopId1": 4,
        "shopId2": 5,
        "rarityId": 3,
        "baseId": 10040,
        "adjustId": 50014871,
        "pickupId": 50017922,
        "ticketItemId": 4001,
        "gachaGroupId": 0,
        "drawNum1": 1,
        "drawNum2": 11,
        "extraGroupId1": 932,
        "extraGroupId2": 0,
        "extraAddCount1": 1,
        "extraAddCount2": 0,
        "freeDrawFlag": 0,
        "maxDrawNum": 0,
        "beforeGachaId": 101,
        "beforeDrawNum": 1,
        "openedAt": 1744016400,
        "closedAt": 1744603199,
        "condQuestId": 1000002,
        "condQuestPhase": 1,
        "detailUrl": "/25_fzcix/frnr_pu_b",
        "bannerQuestId": 1000002,
        "bannerQuestPhase": 1,
        "flag": 34,
        "gachaListGroupId": 1,
        "featurePickupRarityGroupId": 10002
    },
    {
        "id": 50027511,
        "name": "【週替り】 楊貴妃ピックアップ召喚",
        "imageId": 82912,
        "priority": 2501260,
        "warId": 100,
        "gachaSlot": 2501260,
        "type": 1,
        "shopId1": 4,
        "shopId2": 5,
        "rarityId": 3,
        "baseId": 10040,
        "adjustId": 50014881,
        "pickupId": 50017932,
        "ticketItemId": 4001,
        "gachaGroupId": 0,
        "drawNum1": 1,
        "drawNum2": 11,
        "extraGroupId1": 933,
        "extraGroupId2": 0,
        "extraAddCount1": 1,
        "extraAddCount2": 0,
        "freeDrawFlag": 0,
        "maxDrawNum": 0,
        "beforeGachaId": 101,
        "beforeDrawNum": 1,
        "openedAt": 1744016400,
        "closedAt": 1744603199,
        "condQuestId": 1000002,
        "condQuestPhase": 1,
        "detailUrl": "/25_fzcix/frnr_pu_c",
        "bannerQuestId": 1000002,
        "bannerQuestPhase": 1,
        "flag": 34,
        "gachaListGroupId": 1,
        "featurePickupRarityGroupId": 10002
    },
    {
        "id": 50027521,
        "name": "【週替り】 ボイジャーピックアップ召喚",
        "imageId": 82913,
        "priority": 2501250,
        "warId": 100,
        "gachaSlot": 2501250,
        "type": 1,
        "shopId1": 4,
        "shopId2": 5,
        "rarityId": 3,
        "baseId": 10040,
        "adjustId": 50014891,
        "pickupId": 50017942,
        "ticketItemId": 4001,
        "gachaGroupId": 0,
        "drawNum1": 1,
        "drawNum2": 11,
        "extraGroupId1": 934,
        "extraGroupId2": 0,
        "extraAddCount1": 1,
        "extraAddCount2": 0,
        "freeDrawFlag": 0,
        "maxDrawNum": 0,
        "beforeGachaId": 101,
        "beforeDrawNum": 1,
        "openedAt": 1744016400,
        "closedAt": 1744603199,
        "condQuestId": 1000002,
        "condQuestPhase": 1,
        "detailUrl": "/25_fzcix/frnr_pu_d",
        "bannerQuestId": 1000002,
        "bannerQuestPhase": 1,
        "flag": 34,
        "gachaListGroupId": 1,
        "featurePickupRarityGroupId": 10002
    },
    {
        "id": 50027531,
        "name": "【週替り】 アビゲイル･ウィリアムズ〔夏〕ピックアップ召喚",
        "imageId": 82914,
        "priority": 2501240,
        "warId": 100,
        "gachaSlot": 2501240,
        "type": 1,
        "shopId1": 4,
        "shopId2": 5,
        "rarityId": 3,
        "baseId": 10040,
        "adjustId": 50014901,
        "pickupId": 50017952,
        "ticketItemId": 4001,
        "gachaGroupId": 0,
        "drawNum1": 1,
        "drawNum2": 11,
        "extraGroupId1": 935,
        "extraGroupId2": 0,
        "extraAddCount1": 1,
        "extraAddCount2": 0,
        "freeDrawFlag": 0,
        "maxDrawNum": 0,
        "beforeGachaId": 101,
        "beforeDrawNum": 1,
        "openedAt": 1744016400,
        "closedAt": 1744603199,
        "condQuestId": 1000002,
        "condQuestPhase": 1,
        "detailUrl": "/25_fzcix/frnr_pu_e",
        "bannerQuestId": 1000002,
        "bannerQuestPhase": 1,
        "flag": 34,
        "gachaListGroupId": 1,
        "featurePickupRarityGroupId": 10002
    },
    {
        "id": 50027541,
        "name": "【週替り】 ヴァン･ゴッホピックアップ召喚",
        "imageId": 82915,
        "priority": 2501230,
        "warId": 100,
        "gachaSlot": 2501230,
        "type": 1,
        "shopId1": 4,
        "shopId2": 5,
        "rarityId": 3,
        "baseId": 10040,
        "adjustId": 50014911,
        "pickupId": 50017962,
        "ticketItemId": 4001,
        "gachaGroupId": 0,
        "drawNum1": 1,
        "drawNum2": 11,
        "extraGroupId1": 936,
        "extraGroupId2": 0,
        "extraAddCount1": 1,
        "extraAddCount2": 0,
        "freeDrawFlag": 0,
        "maxDrawNum": 0,
        "beforeGachaId": 101,
        "beforeDrawNum": 1,
        "openedAt": 1744016400,
        "closedAt": 1744603199,
        "condQuestId": 1000002,
        "condQuestPhase": 1,
        "detailUrl": "/25_fzcix/frnr_pu_f",
        "bannerQuestId": 1000002,
        "bannerQuestPhase": 1,
        "flag": 34,
        "gachaListGroupId": 1,
        "featurePickupRarityGroupId": 10002
    },
    {
        "id": 50027551,
        "name": "【週替り】 ジャック･ド･モレーピックアップ召喚",
        "imageId": 82916,
        "priority": 2501220,
        "warId": 100,
        "gachaSlot": 2501220,
        "type": 1,
        "shopId1": 4,
        "shopId2": 5,
        "rarityId": 3,
        "baseId": 10040,
        "adjustId": 50014921,
        "pickupId": 50017972,
        "ticketItemId": 4001,
        "gachaGroupId": 0,
        "drawNum1": 1,
        "drawNum2": 11,
        "extraGroupId1": 937,
        "extraGroupId2": 0,
        "extraAddCount1": 1,
        "extraAddCount2": 0,
        "freeDrawFlag": 0,
        "maxDrawNum": 0,
        "beforeGachaId": 101,
        "beforeDrawNum": 1,
        "openedAt": 1744016400,
        "closedAt": 1744603199,
        "condQuestId": 1000002,
        "condQuestPhase": 1,
        "detailUrl": "/25_fzcix/frnr_pu_g",
        "bannerQuestId": 1000002,
        "bannerQuestPhase": 1,
        "flag": 34,
        "gachaListGroupId": 1,
        "featurePickupRarityGroupId": 10002
    },
    {
        "id": 50027561,
        "name": "【週替り】 闇のコヤンスカヤピックアップ召喚",
        "imageId": 82917,
        "priority": 2501210,
        "warId": 100,
        "gachaSlot": 2501210,
        "type": 1,
        "shopId1": 4,
        "shopId2": 5,
        "rarityId": 3,
        "baseId": 10040,
        "adjustId": 50014931,
        "pickupId": 50017982,
        "ticketItemId": 4001,
        "gachaGroupId": 0,
        "drawNum1": 1,
        "drawNum2": 11,
        "extraGroupId1": 938,
        "extraGroupId2": 0,
        "extraAddCount1": 1,
        "extraAddCount2": 0,
        "freeDrawFlag": 0,
        "maxDrawNum": 0,
        "beforeGachaId": 101,
        "beforeDrawNum": 1,
        "openedAt": 1744016400,
        "closedAt": 1744603199,
        "condQuestId": 1000002,
        "condQuestPhase": 1,
        "detailUrl": "/25_fzcix/frnr_pu_h",
        "bannerQuestId": 1000002,
        "bannerQuestPhase": 1,
        "flag": 34,
        "gachaListGroupId": 1,
        "featurePickupRarityGroupId": 10002
    },
    {
        "id": 50027571,
        "name": "【週替り】 ククルカンピックアップ召喚",
        "imageId": 82918,
        "priority": 2501200,
        "warId": 100,
        "gachaSlot": 2501200,
        "type": 1,
        "shopId1": 4,
        "shopId2": 5,
        "rarityId": 3,
        "baseId": 10040,
        "adjustId": 50014941,
        "pickupId": 50017992,
        "ticketItemId": 4001,
        "gachaGroupId": 0,
        "drawNum1": 1,
        "drawNum2": 11,
        "extraGroupId1": 939,
        "extraGroupId2": 0,
        "extraAddCount1": 1,
        "extraAddCount2": 0,
        "freeDrawFlag": 0,
        "maxDrawNum": 0,
        "beforeGachaId": 101,
        "beforeDrawNum": 1,
        "openedAt": 1744016400,
        "closedAt": 1744603199,
        "condQuestId": 1000002,
        "condQuestPhase": 1,
        "detailUrl": "/25_fzcix/frnr_pu_i",
        "bannerQuestId": 1000002,
        "bannerQuestPhase": 1,
        "flag": 34,
        "gachaListGroupId": 1,
        "featurePickupRarityGroupId": 10002
    },
    {
        "id": 50027581,
        "name": "【週替り】 ワンジナピックアップ召喚",
        "imageId": 82919,
        "priority": 2501190,
        "warId": 100,
        "gachaSlot": 2501190,
        "type": 1,
        "shopId1": 4,
        "shopId2": 5,
        "rarityId": 3,
        "baseId": 10040,
        "adjustId": 50014951,
        "pickupId": 50018002,
        "ticketItemId": 4001,
        "gachaGroupId": 0,
        "drawNum1": 1,
        "drawNum2": 11,
        "extraGroupId1": 940,
        "extraGroupId2": 0,
        "extraAddCount1": 1,
        "extraAddCount2": 0,
        "freeDrawFlag": 0,
        "maxDrawNum": 0,
        "beforeGachaId": 101,
        "beforeDrawNum": 1,
        "openedAt": 1744016400,
        "closedAt": 1744603199,
        "condQuestId": 1000002,
        "condQuestPhase": 1,
        "detailUrl": "/25_fzcix/frnr_pu_j",
        "bannerQuestId": 1000002,
        "bannerQuestPhase": 1,
        "flag": 34,
        "gachaListGroupId": 1,
        "featurePickupRarityGroupId": 10002
    },
    {
        "id": 50027591,
        "name": "【週替り】 蒼崎青子ピックアップ召喚",
        "imageId": 82920,
        "priority": 2501180,
        "warId": 100,
        "gachaSlot": 2501180,
        "type": 1,
        "shopId1": 4,
        "shopId2": 5,
        "rarityId": 3,
        "baseId": 10040,
        "adjustId": 50014961,
        "pickupId": 50018012,
        "ticketItemId": 4001,
        "gachaGroupId": 0,
        "drawNum1": 1,
        "drawNum2": 11,
        "extraGroupId1": 941,
        "extraGroupId2": 0,
        "extraAddCount1": 1,
        "extraAddCount2": 0,
        "freeDrawFlag": 0,
        "maxDrawNum": 0,
        "beforeGachaId": 101,
        "beforeDrawNum": 1,
        "openedAt": 1744016400,
        "closedAt": 1744603199,
        "condQuestId": 1000002,
        "condQuestPhase": 1,
        "detailUrl": "/25_fzcix/frnr_pu_k",
        "bannerQuestId": 1000002,
        "bannerQuestPhase": 1,
        "flag": 34,
        "gachaListGroupId": 1,
        "featurePickupRarityGroupId": 10002
    }
]